feng_libs/__init__.py
feng_libs/__main__.py
feng_libs/feng_libs.py
feng_libs/file_libs/__init__.py
feng_libs/file_libs/pdf_libs.py
feng_libs/image_libs/__init__.py
feng_libs/image_libs/template_match.py
feng_libs-0.2.dist-info/METADATA
feng_libs-0.2.dist-info/WHEEL
feng_libs-0.2.dist-info/entry_points.txt
feng_libs-0.2.dist-info/top_level.txt
feng_libs-0.2.dist-info/RECORD
