Metadata-Version: 2.1
Name: feng-libs
Version: 0.2
Summary: 常用工具库
Home-page: https://github.com/tenqaz/feng_libs
Author: jim
Author-email: zhengwenfeng37@gmail.com
License: jims Licence
Platform: any
Classifier: Intended Audience :: Developers
Classifier: Operating System :: OS Independent
Classifier: Natural Language :: Chinese (Simplified)
Classifier: Programming Language :: Python
Classifier: Programming Language :: Python :: 3.4
Classifier: Programming Language :: Python :: 3.5
Classifier: Topic :: Utilities
Requires-Dist: fire
Requires-Dist: PyPDF2
Requires-Dist: opencv-python
